ET_Client.py
FuelSDK/__init__.py
FuelSDK/client.py
FuelSDK/objects.py
FuelSDK/rest.py
FuelSDK/suds_patch.py
Fever_FuelSDK-1.3.2.dist-info/LICENSE
Fever_FuelSDK-1.3.2.dist-info/METADATA
Fever_FuelSDK-1.3.2.dist-info/WHEEL
Fever_FuelSDK-1.3.2.dist-info/top_level.txt
Fever_FuelSDK-1.3.2.dist-info/RECORD
